split_bill/__init__.py
split_bill/optimize.py
split_bill-1.0.0.dist-info/LICENSE
split_bill-1.0.0.dist-info/WHEEL
split_bill-1.0.0.dist-info/METADATA
split_bill-1.0.0.dist-info/RECORD
